minimax_cli/__init__.py
minimax_cli/cli.py
minimax_cli-0.4.1.dist-info/licenses/LICENSE
minimax_cli-0.4.1.dist-info/METADATA
minimax_cli-0.4.1.dist-info/WHEEL
minimax_cli-0.4.1.dist-info/entry_points.txt
minimax_cli-0.4.1.dist-info/top_level.txt
minimax_cli-0.4.1.dist-info/RECORD
