Metadata-Version: 2.4
Name: MiniMax-CLI
Version: 0.4.1
Summary: Unofficial MiniMax CLI - downloads and runs the Rust binary
Author: Hmbown
Project-URL: Homepage, https://github.com/Hmbown/MiniMax-CLI
Project-URL: Source, https://github.com/Hmbown/MiniMax-CLI
Keywords: minimax,cli,ai,agent
Classifier: Development Status :: 3 - Alpha
Classifier: Programming Language :: Python :: 3
Classifier: License :: OSI Approved :: MIT License
Classifier: Operating System :: OS Independent
Requires-Python: >=3.8
License-File: LICENSE
Dynamic: license-file
